azure_maps_jupyter/__init__.py
azure_maps_jupyter/_version.py
azure_maps_jupyter/basemaps.py
azure_maps_jupyter/leaflet.py
azure_maps_jupyter/projections.py
azure_maps_jupyter/velocity.py
azure_maps_jupyter/xarray_ds.py
azure_maps_jupyter/external/__init__.py
azure_maps_jupyter/external/here.py
azure_maps_jupyter/labextension/package.json
azure_maps_jupyter/labextension/static/056dcd0b0dea7c78019243311551d64b.png
azure_maps_jupyter/labextension/static/07f16cd155661436fe27959eab15c820.png
azure_maps_jupyter/labextension/static/0b50583aa1b8ff230b57b92263e47a3e.png
azure_maps_jupyter/labextension/static/0f2c10250081cf1bd9a4d2250b80dba6.png
azure_maps_jupyter/labextension/static/138.410f06b0d3f50f6a7c1a.js
azure_maps_jupyter/labextension/static/2273e3d8ad9264b7daa5bdbf8e6b47f8.png
azure_maps_jupyter/labextension/static/243.de3283a4d6c29997826e.js
azure_maps_jupyter/labextension/static/243.de3283a4d6c29997826e.js.LICENSE.txt
azure_maps_jupyter/labextension/static/270.580638860ab552a40f69.js
azure_maps_jupyter/labextension/static/270.580638860ab552a40f69.js.LICENSE.txt
azure_maps_jupyter/labextension/static/292.4107fc80f490ac63e379.js
azure_maps_jupyter/labextension/static/340.b813e0996b4847b4fa5f.js
azure_maps_jupyter/labextension/static/35.eb4b6d6bf1ffeee78ab0.js
azure_maps_jupyter/labextension/static/35ae4b5f1bf198c6d955618b85710d05.png
azure_maps_jupyter/labextension/static/366.ff8b90650c5a14bd07a2.js
azure_maps_jupyter/labextension/static/401d815dc206b8dc1b17cd0e37695975.png
azure_maps_jupyter/labextension/static/408.24489a1928f1ef461a23.js
azure_maps_jupyter/labextension/static/44a526eed258222515aa21eaffd14a96.png
azure_maps_jupyter/labextension/static/473ee081160a469c95199d70e78f55fa.png
azure_maps_jupyter/labextension/static/4f0283c6ce28e888000e978e537a6a56.png
azure_maps_jupyter/labextension/static/549b33bab7247b619c0292995f5a906b.png
azure_maps_jupyter/labextension/static/550.8c25f64dcc710ad89f76.js
azure_maps_jupyter-0.0.3.dist-info/LICENSE
azure_maps_jupyter-0.0.3.dist-info/METADATA
azure_maps_jupyter-0.0.3.dist-info/WHEEL
azure_maps_jupyter-0.0.3.dist-info/top_level.txt
azure_maps_jupyter-0.0.3.dist-info/RECORD
